odoo/addons/delivery_correos_express/README.rst
odoo/addons/delivery_correos_express/__init__.py
odoo/addons/delivery_correos_express/__manifest__.py
odoo/addons/delivery_correos_express/doc/GrabacionEnvios/DC_SP_ apiRestSeguimientoEnviosk8s_v01.00.pdf
odoo/addons/delivery_correos_express/doc/GrabacionEnvios/DC_SP_WS_GrabacionEnviosRest_v03.07.pdf
odoo/addons/delivery_correos_express/doc/GrabacionEnvios/DC_SP_WS_ListEnviosRest_v01.01.pdf
odoo/addons/delivery_correos_express/doc/GrabacionEnvios/DC_SP_WS_apiRestEtiquetaTransporte_v01.01.pdf
odoo/addons/delivery_correos_express/doc/GrabacionRecogidas/DC_SP_Seguimiento_Recogidak8s_v01.00.pdf
odoo/addons/delivery_correos_express/doc/GrabacionRecogidas/DC_SP_WS_GrabacionRecogidaRest_v1.4.pdf
odoo/addons/delivery_correos_express/i18n/delivery_correos_express.pot
odoo/addons/delivery_correos_express/i18n/es.po
odoo/addons/delivery_correos_express/models/__init__.py
odoo/addons/delivery_correos_express/models/correos_express_request.py
odoo/addons/delivery_correos_express/models/delivery_carrier.py
odoo/addons/delivery_correos_express/models/stock_picking.py
odoo/addons/delivery_correos_express/readme/CONFIGURE.rst
odoo/addons/delivery_correos_express/readme/CONTRIBUTORS.rst
odoo/addons/delivery_correos_express/readme/DESCRIPTION.rst
odoo/addons/delivery_correos_express/readme/INSTALL.rst
odoo/addons/delivery_correos_express/readme/ROADMAP.rst
odoo/addons/delivery_correos_express/readme/USAGE.rst
odoo/addons/delivery_correos_express/static/description/icon.png
odoo/addons/delivery_correos_express/static/description/index.html
odoo/addons/delivery_correos_express/tests/__init__.py
odoo/addons/delivery_correos_express/tests/test_delivery_correos_express.py
odoo/addons/delivery_correos_express/views/delivery_carrier_view.xml
odoo/addons/delivery_correos_express/views/stock_picking_views.xml
odoo14_addon_delivery_correos_express-14.0.1.0.1.dist-info/METADATA
odoo14_addon_delivery_correos_express-14.0.1.0.1.dist-info/WHEEL
odoo14_addon_delivery_correos_express-14.0.1.0.1.dist-info/top_level.txt
odoo14_addon_delivery_correos_express-14.0.1.0.1.dist-info/RECORD
